prioritization_discovery/__init__.py
prioritization_discovery/config.py
prioritization_discovery/discovery.py
prioritization_discovery/rules.py
prioritization_discovery-0.4.4.dist-info/LICENSE
prioritization_discovery-0.4.4.dist-info/METADATA
prioritization_discovery-0.4.4.dist-info/WHEEL
prioritization_discovery-0.4.4.dist-info/RECORD
