Metadata-Version: 2.1
Name: prioritization-discovery
Version: 0.4.4
Summary: Python algorithm to discover, from an event log, prioritization rules that lead to one activity instance to be executed before another.
Author: David Chapela de la Campa
Author-email: david.chapela.delacampa@gmail.com
Requires-Python: >=3.9,<3.12
Classifier: Programming Language :: Python :: 3
Classifier: Programming Language :: Python :: 3.9
Classifier: Programming Language :: Python :: 3.10
Classifier: Programming Language :: Python :: 3.11
Requires-Dist: pandas (>=2.0.2,<3.0.0)
Requires-Dist: pandasql (>=0.7.3,<0.8.0)
Requires-Dist: scikit-learn (>=1.2.2,<2.0.0)
